LICENSE.txt
MANIFEST.in
README.md
setup.cfg
setup.py
docs/source/overview.rst
pappyproxy/__init__.py
pappyproxy/__main__.py
pappyproxy/colors.py
pappyproxy/comm.py
pappyproxy/compress.py
pappyproxy/config.py
pappyproxy/console.py
pappyproxy/context.py
pappyproxy/crypto.py
pappyproxy/default_global_config.json
pappyproxy/default_user_config.json
pappyproxy/http.py
pappyproxy/iter.py
pappyproxy/macros.py
pappyproxy/mangle.py
pappyproxy/pappy.py
pappyproxy/plugin.py
pappyproxy/proxy.py
pappyproxy/repeater.py
pappyproxy/requestcache.py
pappyproxy/session.py
pappyproxy/site.py
pappyproxy/sortedcollection.py
pappyproxy/util.py
pappyproxy.egg-info/PKG-INFO
pappyproxy.egg-info/SOURCES.txt
pappyproxy.egg-info/dependency_links.txt
pappyproxy.egg-info/entry_points.txt
pappyproxy.egg-info/requires.txt
pappyproxy.egg-info/top_level.txt
pappyproxy/lists/path_traversal.txt
pappyproxy/lists/fuzzdb/_copyright.txt
pappyproxy/lists/fuzzdb/attack/all-attacks/all-attacks-unix.txt
pappyproxy/lists/fuzzdb/attack/all-attacks/all-attacks-win.txt
pappyproxy/lists/fuzzdb/attack/all-attacks/all-attacks-xplatform.txt
pappyproxy/lists/fuzzdb/attack/business-logic/CommonDebugParamNames.txt
pappyproxy/lists/fuzzdb/attack/business-logic/CommonMethodNames.txt
pappyproxy/lists/fuzzdb/attack/control-chars/HexValsAllBytes.txt
pappyproxy/lists/fuzzdb/attack/control-chars/NullByteRepresentations.txt
pappyproxy/lists/fuzzdb/attack/disclosure-directory/directory-indexing-generic.txt
pappyproxy/lists/fuzzdb/attack/disclosure-localpaths/unix/common-unix-httpd-log-locations.txt
pappyproxy/lists/fuzzdb/attack/disclosure-source/source-disc-cmd-exec-traversal.txt
pappyproxy/lists/fuzzdb/attack/disclosure-source/source-disclosure-generic.txt
pappyproxy/lists/fuzzdb/attack/disclosure-source/source-disclosure-microsoft.txt
pappyproxy/lists/fuzzdb/attack/email/invalid-email-addresses.txt
pappyproxy/lists/fuzzdb/attack/email/valid-email-addresses.txt
pappyproxy/lists/fuzzdb/attack/file-upload/alt-extensions-asp.txt
pappyproxy/lists/fuzzdb/attack/file-upload/alt-extensions-coldfusion.txt
pappyproxy/lists/fuzzdb/attack/file-upload/alt-extensions-jsp.txt
pappyproxy/lists/fuzzdb/attack/file-upload/alt-extensions-perl.txt
