Metadata-Version: 1.1
Name: pappyproxy
Version: 0.2.14
Summary: The Pappy Intercepting Proxy
Home-page: https://www.github.com/roglew/pappy-proxy
Author: Rob Glew
Author-email: rglew56@gmail.com
License: MIT
Download-URL: https://github.com/roglew/pappy-proxy/archive/0.2.14.tar.gz
Keywords: http proxy hacking 1337hax pwnurmum
Platform: UNKNOWN
Classifier: Intended Audience :: Developers
Classifier: Intended Audience :: Information Technology
Classifier: Operating System :: MacOS
Classifier: Operating System :: POSIX :: Linux
Classifier: Development Status :: 2 - Pre-Alpha
Classifier: Programming Language :: Python :: 2.6
Classifier: Programming Language :: Python :: 2.7
Classifier: License :: OSI Approved :: MIT License
Classifier: Topic :: Security
